{
  "sample_id": "demo",
  "items": [
    {
      "segment_id": "0_0",
      "contour_id": 0,
      "closed_parent": true,
      "is_closed": true,
      "line_like": true,
      "elongation": 75.04924233299137,
      "point_count": 484,
      "candidates": [
        {
          "type": "line",
          "params": {
            "p1": [
              39.246418325362825,
              299.2698361600328
            ],
            "p2": [
              280.7408779019112,
              380.76780724299647
            ]
          },
          "param_count": 2,
          "rmse": 0.9056833317813556,
          "inlier_ratio": 0.859504132231405,
          "inlier_count": 416
        },
        {
          "type": "arc",
          "params": {
            "cx": 169.32053490324677,
            "cy": 450.5894032253092,
            "r": 103.76028580321645,
            "start_angle": 269.29019955338265,
            "end_angle": 307.4025573976852,
            "span": 38.11235784430255
          },
          "param_count": 4,
          "rmse": 1.296517181720652,
          "coverage": 0.10586766067861819,
          "inlier_ratio": 0.1921487603305785,
          "inlier_count": 93
        },
        {
          "type": "circle",
          "params": {
            "cx": 363.25689104571615,
            "cy": -252.35239782228163,
            "r": 630.6799173319602
          },
          "param_count": 3,
          "rmse": 3.6525219564069182,
          "inlier_ratio": 0.7871900826446281,
          "inlier_count": 381,
          "coverage": 0.06389855302407818
        },
        {
          "type": "bspline",
          "params": {
            "degree": 3,
            "closed": false,
            "control_points": [
              [
                40.0,
                299.0
              ],
              [
                107.0,
                323.0
              ],
              [
                176.0,
                346.0
              ],
              [
                245.0,
                369.0
              ],
              [
                248.0,
                368.0
              ],
              [
                179.0,
                345.0
              ],
              [
                110.0,
                322.0
              ],
              [
                41.0,
                299.0
              ]
            ]
          },
          "param_count": 16,
          "rmse": 7.5986983923752955
        }
      ]
    },
    {
      "segment_id": "1_1",
      "contour_id": 1,
      "closed_parent": true,
      "is_closed": true,
      "line_like": false,
      "elongation": 2.0775731654804743,
      "point_count": 626,
      "candidates": [
        {
          "type": "circle",
          "params": {
            "cx": 419.77660641497187,
            "cy": 339.7217548552817,
            "r": 99.90028310991246
          },
          "param_count": 3,
          "rmse": 0.8591907236335543,
          "inlier_ratio": 0.8466453674121406,
          "inlier_count": 530,
          "coverage": 0.5590103293090776
        },
        {
          "type": "ellipse",
          "params": {
            "cx": 427.0659484863281,
            "cy": 334.5552062988281,
            "ax": 103.88733673095703,
            "by": 108.85009765625,
            "angle": 53.16279602050781
          },
          "param_count": 5,
          "rmse": 1.8591915370218084,
          "inlier_ratio": 0.5926517571884984,
          "inlier_count": 371
        },
        {
          "type": "arc",
          "params": {
            "cx": 419.5475433495813,
            "cy": 340.5704870458705,
            "r": 99.7691117240535,
            "start_angle": 28.976852907432203,
            "end_angle": 231.11966653725023,
            "span": 202.14281362981802
          },
          "param_count": 4,
          "rmse": 0.8426171724171869,
          "coverage": 0.5615078156383834,
          "inlier_ratio": 0.8162939297124601,
          "inlier_count": 511
        },
        {
          "type": "line",
          "params": {
            "p1": [
              319.19423735655573,
              324.06320261958774
            ],
            "p2": [
              322.96073533946293,
              372.0815191000194
            ]
          },
          "param_count": 2,
          "rmse": 0.9010166568706984,
          "inlier_ratio": 0.1134185303514377,
          "inlier_count": 71
        },
        {
          "type": "bspline",
          "params": {
            "degree": 3,
            "closed": true,
            "control_points": [
              [
                356.0,
                262.0
              ],
              [
                320.0,
                350.0
              ],
              [
                376.0,
                431.0
              ],
              [
                465.0,
                430.0
              ],
              [
                470.0,
                426.0
              ],
              [
                381.0,
                431.0
              ],
              [
                322.0,
                352.0
              ],
              [
                357.0,
                263.0
              ]
            ]
          },
          "param_count": 16,
          "rmse": 13.367408001753034
        }
      ]
    },
    {
      "segment_id": "2_2",
      "contour_id": 2,
      "closed_parent": true,
      "is_closed": true,
      "line_like": false,
      "elongation": 1.5124478894945141,
      "point_count": 551,
      "candidates": [
        {
          "type": "circle",
          "params": {
            "cx": 375.41550676634654,
            "cy": 254.16789073791676,
            "r": 175.682844666249
          },
          "param_count": 3,
          "rmse": 0.6382021182419771,
          "inlier_ratio": 0.3702359346642468,
          "inlier_count": 204,
          "coverage": 0.32198641309350584
        },
        {
          "type": "ellipse",
          "params": {
            "cx": 419.9875183105469,
            "cy": 160.0008544921875,
            "ax": 70.89271545410156,
            "by": 120.84278106689453,
            "angle": 115.03726196289062
          },
          "param_count": 5,
          "rmse": 0.46419699894676997,
          "inlier_ratio": 1.0,
          "inlier_count": 551
        },
        {
          "type": "arc",
          "params": {
            "cx": 373.52661282660614,
            "cy": 259.07380860788186,
            "r": 180.74931740287067,
            "start_angle": 260.53317226842336,
            "end_angle": 329.91405905060583,
            "span": 69.38088678218242
          },
          "param_count": 4,
          "rmse": 0.48230637497456097,
          "coverage": 0.19272468550606225,
          "inlier_ratio": 0.3502722323049002,
          "inlier_count": 193
        },
        {
          "type": "line",
          "params": {
            "p1": [
              378.5480412231396,
              220.25626641112277
            ],
            "p2": [
              436.59061601317825,
              241.1379191525776
            ]
          },
          "param_count": 2,
          "rmse": 0.7110186503629893,
          "inlier_ratio": 0.10163339382940109,
          "inlier_count": 56
        },
        {
          "type": "bspline",
          "params": {
            "degree": 3,
            "closed": true,
            "control_points": [
              [
                363.0,
                78.0
              ],
              [
                307.0,
                131.0
              ],
              [
                359.0,
                206.0
              ],
              [
                437.0,
                240.0
              ],
              [
                516.0,
                227.0
              ],
              [
                519.0,
                151.0
              ],
              [
                443.0,
                93.0
              ],
              [
                364.0,
                78.0
              ]
            ]
          },
          "param_count": 16,
          "rmse": 7.613952662294402
        }
      ]
    },
    {
      "segment_id": "3_3",
      "contour_id": 3,
      "closed_parent": true,
      "is_closed": true,
      "line_like": false,
      "elongation": 1.0,
      "point_count": 456,
      "candidates": [
        {
          "type": "circle",
          "params": {
            "cx": 150.0000000000001,
            "cy": 150.00000000000003,
            "r": 80.39829578363151
          },
          "param_count": 3,
          "rmse": 0.26706829824029704,
          "inlier_ratio": 1.0,
          "inlier_count": 456,
          "coverage": 0.9971972179901005
        },
        {
          "type": "ellipse",
          "params": {
            "cx": 150.0,
            "cy": 150.0,
            "ax": 80.40007019042969,
            "by": 80.40007019042969,
            "angle": 0.0
          },
          "param_count": 5,
          "rmse": 0.5342552218607011,
          "inlier_ratio": 1.0,
          "inlier_count": 456
        },
        {
          "type": "arc",
          "params": {
            "cx": 150.11779455079716,
            "cy": 149.95144531537287,
            "r": 80.48160756936612,
            "start_angle": 351.49090087935053,
            "end_angle": 306.3976396752671,
            "span": 314.90673879591657
          },
          "param_count": 4,
          "rmse": 0.2624450874283101,
          "coverage": 0.8747409410997682,
          "inlier_ratio": 0.6907894736842105,
          "inlier_count": 315
        },
        {
          "type": "line",
          "params": {
            "p1": [
              133.02562787703053,
              69.96572324593811
            ],
            "p2": [
              171.02707550625598,
              70.90737836942058
            ]
          },
          "param_count": 2,
          "rmse": 0.6517560098646236,
          "inlier_ratio": 0.08552631578947369,
          "inlier_count": 39
        },
        {
          "type": "bspline",
          "params": {
            "degree": 3,
            "closed": true,
            "control_points": [
              [
                150.0,
                69.0
              ],
              [
                86.0,
                101.0
              ],
              [
                71.0,
                166.0
              ],
              [
                117.0,
                223.0
              ],
              [
                182.0,
                224.0
              ],
              [
                229.0,
                167.0
              ],
              [
                215.0,
                102.0
              ],
              [
                151.0,
                70.0
              ]
            ]
          },
          "param_count": 16,
          "rmse": 5.6565927140248355
        }
      ]
    }
  ]
}